tradingindicators/__init__.py
tradingindicators/indicators.py
tradingindicators-1.0.1.dist-info/LICENSE
tradingindicators-1.0.1.dist-info/METADATA
tradingindicators-1.0.1.dist-info/WHEEL
tradingindicators-1.0.1.dist-info/top_level.txt
tradingindicators-1.0.1.dist-info/RECORD
