Metadata-Version: 2.1
Name: tradingindicators
Version: 1.0.1
Summary: Calculator for the most important trading indicators.
Home-page: https://github.com/array-drian/tradingindicators
Author: Array-drian
Author-email: adrian.mahn@gmx.net
License: MIT
License-File: LICENSE
